stairs_mro/__init__.py
stairs_mro/networks/DefectRes.py
stairs_mro/networks/WorkDefectCount.py
stairs_mro/networks/WorkDefectNet.py
stairs_mro/networks/WorkResNet.py
stairs_mro/networks/__init__.py
stairs_mro-0.2.1.dist-info/METADATA
stairs_mro-0.2.1.dist-info/WHEEL
stairs_mro-0.2.1.dist-info/RECORD
