Metadata-Version: 2.1
Name: stairs-mro
Version: 0.2.1
Summary: 
Author: jrzkaminski
Author-email: 86363785+jrzkaminski@users.noreply.github.com
Requires-Python: >=3.9,<3.11
Classifier: Programming Language :: Python :: 3
Classifier: Programming Language :: Python :: 3.9
Classifier: Programming Language :: Python :: 3.10
Requires-Dist: bamt-light (==0.0.2)
Requires-Dist: scikit-learn (>=1.3.2)
Requires-Dist: scipy (>=1.8.0)
